prot2d/Classes.py
prot2d/Graphical.py
prot2d/Main_functions.py
prot2d/SF_database/db_info.tsv
prot2d/SF_database/foldseek_db/db
prot2d/SF_database/foldseek_db/db.dbtype
prot2d/SF_database/foldseek_db/db.index
prot2d/SF_database/foldseek_db/db.lookup
prot2d/SF_database/foldseek_db/db.source
prot2d/SF_database/foldseek_db/db_ca
prot2d/SF_database/foldseek_db/db_ca.dbtype
prot2d/SF_database/foldseek_db/db_ca.index
prot2d/SF_database/foldseek_db/db_h
prot2d/SF_database/foldseek_db/db_h.dbtype
prot2d/SF_database/foldseek_db/db_h.index
prot2d/SF_database/foldseek_db/db_ss
prot2d/SF_database/foldseek_db/db_ss.dbtype
prot2d/SF_database/foldseek_db/db_ss.index
prot2d/Structure_Database.py
prot2d/__init__.py
prot2d/cli.py
prot2d/flexUSER_database/db_info.tsv
prot2d/flexUSER_database/foldseek_db/db
prot2d/flexUSER_database/foldseek_db/db.dbtype
prot2d/flexUSER_database/foldseek_db/db.index
prot2d/flexUSER_database/foldseek_db/db.lookup
prot2d/flexUSER_database/foldseek_db/db.source
prot2d/flexUSER_database/foldseek_db/db_ca
prot2d/flexUSER_database/foldseek_db/db_ca.dbtype
prot2d/flexUSER_database/foldseek_db/db_ca.index
prot2d/flexUSER_database/foldseek_db/db_h
prot2d/flexUSER_database/foldseek_db/db_h.dbtype
prot2d/flexUSER_database/foldseek_db/db_h.index
prot2d/flexUSER_database/foldseek_db/db_ss
prot2d/flexUSER_database/foldseek_db/db_ss.dbtype
prot2d/flexUSER_database/foldseek_db/db_ss.index
prot2d/main.py
prot2d/utils.py
prot2d-0.5.7.dist-info/METADATA
prot2d-0.5.7.dist-info/WHEEL
prot2d-0.5.7.dist-info/entry_points.txt
prot2d-0.5.7.dist-info/RECORD
