Metadata-Version: 2.1
Name: prot2d
Version: 0.5.7
Summary: Python package for creating simplified 2D protein visualisations. Specialised on showing differences and similaritys between proteins from the same protein family.
Author: constantincarl
Author-email: ge37goy@mytum.de
Requires-Python: >=3.10,<3.13
Classifier: Programming Language :: Python :: 3
Classifier: Programming Language :: Python :: 3.10
Classifier: Programming Language :: Python :: 3.11
Requires-Dist: alphashape (>=1.3.1,<2.0.0)
Requires-Dist: anytree (>=2.12.1,<3.0.0)
Requires-Dist: biopython (>=1.81,<2.0)
Requires-Dist: colour (>=0.1.5,<0.2.0)
Requires-Dist: matplotlib (>=3.8.2,<4.0.0)
Requires-Dist: networkx (>=3.2,<4.0)
Requires-Dist: pandas (>=2.1.3,<3.0.0)
Requires-Dist: scipy (>=1.11.3,<2.0.0)
Requires-Dist: shapely (>=2.0.2,<3.0.0)
Requires-Dist: svgwrite (>=1.4.3,<2.0.0)
Requires-Dist: tqdm (>=4.66.1,<5.0.0)
Requires-Dist: typer (>=0.9.0,<0.10.0)
Requires-Dist: wget (>=3.2,<4.0)
Project-URL: Documentation, https://constantincarl.github.io/prot2d/
Project-URL: Example-Collab, https://colab.research.google.com/drive/17u0twE81kYYspNFsdXUHrCyP33hj0dO6?usp=sharing
Project-URL: Repository, https://github.com/ConstantinCarl/prot2d
Project-URL: Zenodo, https://doi.org/10.5281/zenodo.10674045
